Metadata-Version: 2.1
Name: s3a
Version: 0.7.0
Summary: Semantic labeling made simple
Author-email: Nathan Jessurun <ntjessu@gmail.com>
License: MIT
Project-URL: homepage, https://gitlab.com/s3a/s3a
Keywords: semantic,labeling,image,annotation
Classifier: Development Status :: 3 - Alpha
Classifier: Intended Audience :: Developers
Classifier: Topic :: Software Development :: Build Tools
Classifier: License :: OSI Approved :: MIT License
Classifier: Programming Language :: Python :: 3
Requires-Python: >=3.8
Requires-Dist: numpy
Requires-Dist: pandas (>=1.4.3)
Requires-Dist: scipy
Requires-Dist: scikit-image (>=0.18.1)
Requires-Dist: pyqtgraph (>=0.13.1)
Requires-Dist: Pillow
Requires-Dist: qdarkstyle
Requires-Dist: qtextras (~=0.6.6)
Provides-Extra: full
Requires-Dist: docstring-parser (>=0.10) ; extra == 'full'
Requires-Dist: opencv-python-headless (>=4.1.2.30) ; extra == 'full'
Requires-Dist: PySide6 (~=6.3.0) ; extra == 'full'
